Metadata-Version: 1.1
Name: archive-cdx
Version: 0.2.0
Summary: A library to interact with the archive.org Wayback Machine CDX server.
Home-page: https://github.com/MineRobber9000/archive-cdx
Author: Robert "khuxkm" Miles
Author-email: khuxkm@tilde.ninja
License: UNKNOWN
Project-URL: Bug Reports, https://github.com/MineRobber9000/archive-cdx/issues
Project-URL: Source, https://github.com/MineRobber9000/archive-cdx/
Keywords: wayback-machine cdx
Platform: UNKNOWN
Classifier: Development Status :: 3 - Alpha
Classifier: Intended Audience :: Developers
Classifier: Topic :: Software Development :: Build Tools
Classifier: License :: OSI Approved :: MIT License
Classifier: Programming Language :: Python :: 2
Classifier: Programming Language :: Python :: 2.7
Classifier: Programming Language :: Python :: 3
Classifier: Programming Language :: Python :: 3.4
Classifier: Programming Language :: Python :: 3.5
Classifier: Programming Language :: Python :: 3.6
Classifier: Programming Language :: Python :: 3.7
